cookiebaker/__init__.py
cookiebaker/__pycache__/__init__.cpython-310.pyc
cookiebaker/default_cookiecutter/cookiecutter.json
cookiebaker/default_cookiecutter/hooks/post_gen_project.py
cookiebaker/default_cookiecutter/hooks/pre_gen_project.py
cookiebaker/default_cookiecutter/templates/MIT
cookiebaker/default_cookiecutter/templates/Unlicense
cookiebaker/default_cookiecutter/{{ cookiecutter.__pypi_slug }}/LICENSE.txt
cookiebaker/default_cookiecutter/{{ cookiecutter.__pypi_slug }}/README.md
cookiebaker/default_cookiecutter/{{ cookiecutter.__pypi_slug }}/pyproject.toml
cookiebaker/default_cookiecutter/{{ cookiecutter.__pypi_slug }}/{{ cookiecutter.__gitignore }}
cookiebaker/default_cookiecutter/{{ cookiecutter.__pypi_slug }}/.local/run-acceptance-test
cookiebaker/default_cookiecutter/{{ cookiecutter.__pypi_slug }}/.local/{{ cookiecutter.__gitignore }}
cookiebaker-0.2.1.dist-info/LICENSE.txt
cookiebaker-0.2.1.dist-info/METADATA
cookiebaker-0.2.1.dist-info/WHEEL
cookiebaker-0.2.1.dist-info/entry_points.txt
cookiebaker-0.2.1.dist-info/top_level.txt
cookiebaker-0.2.1.dist-info/RECORD
