Metadata-Version: 2.1
Name: cookiebaker
Version: 0.2.1
Summary: Use `cookiecutter` with existing code and git integration
Author-email: Karl Knechtel <zahlman@proton.me>
License: This is free and unencumbered software released into the public domain.
Project-URL: bugs, https://github.com/zahlman/cookiebaker/issues
Project-URL: changelog, https://github.com/zahlman/cookiebaker/blob/master/changelog.md
Project-URL: homepage, https://github.com/zahlman/cookiebaker
Classifier: Development Status :: 2 - Pre-Alpha
Classifier: Programming Language :: Python :: 3
License-File: LICENSE.txt
Requires-Dist: cookiecutter
